animation.py
calc.py
display.py
domain.py
hydes.py
initCond.py
state.py
hydes-0.0.5.dist-info/LICENSE
hydes-0.0.5.dist-info/METADATA
hydes-0.0.5.dist-info/WHEEL
hydes-0.0.5.dist-info/top_level.txt
hydes-0.0.5.dist-info/RECORD
