Metadata-Version: 2.1
Name: hydes
Version: 0.0.5
Summary: Hydrodinamical equation solver
Home-page: https://github.com/andreuva/HyDES
Author: Andres Vicente Arevalo
Author-email: andres.vicente.arevalo@gmail.com
License: UNKNOWN
Project-URL: Bug Reports, https://github.com/andreuva/HyDES/issues
Project-URL: Funding, https://donate.pypi.org
Project-URL: Source, https://github.com/andreuva/HyDES
Platform: UNKNOWN
Classifier: Programming Language :: Python :: 3
Classifier: License :: OSI Approved :: MIT License
Classifier: Operating System :: OS Independent
Requires-Python: >=3.6
Requires-Dist: numpy
Requires-Dist: matplotlib
Requires-Dist: opencv-python
Provides-Extra: dev
Requires-Dist: setuptools (>=54) ; extra == 'dev'
Requires-Dist: wheel ; extra == 'dev'
Requires-Dist: twine ; extra == 'dev'
